setup.py
fassembler/__init__.py
fassembler/apache.py
fassembler/command.py
fassembler/config.py
fassembler/create-venv-script.py
fassembler/distutilspatch.py
fassembler/environ.py
fassembler/fake_eggs.py
fassembler/filemaker.py
fassembler/namespace.py
fassembler/project.py
fassembler/tasks.py
fassembler/text.py
fassembler/topp.py
fassembler/topp_brainpower.py
fassembler/topp_buildbot.py
fassembler/topp_erroreater.py
fassembler/topp_nymap.py
fassembler/topp_opencore.py
fassembler/topp_products.py
fassembler/topp_windmill.py
fassembler/topp_wordpress.py
fassembler/util.py
fassembler.egg-info/PKG-INFO
fassembler.egg-info/SOURCES.txt
fassembler.egg-info/dependency_links.txt
fassembler.egg-info/entry_points.txt
fassembler.egg-info/not-zip-safe
fassembler.egg-info/requires.txt
fassembler.egg-info/top_level.txt