Metadata-Version: 1.0
Name: fassembler
Version: 0.7
Summary: Builder for OpenCore
Home-page: http://www.coactivate.org/projects/fassembler
Author: Ian Bicking, Paul Winkler, Josh Bronson, Ethan Jucovy
Author-email: opencore-dev@lists.coactivate.org
License: GPL
Platform: UNKNOWN
